{
    "colors": {
        "autoIncrement": true,
        "keyPath": "name",
        "indexes": [
            {
                "name": "name",
                "unique": true
            },
            {
                "name": "entryId",
                "unique": true
            }
        ]
    },
    "patterns": {
        "autoIncrement": true,
        "keyPath": "name",
        "indexes": [
            {
                "name": "name",
                "unique": true
            },
            {
                "name": "entryId",
                "unique": true
            }
        ]
    }
}